app/__init__.py
app/cli.py
app/main.py
app/readers.py
app/processors/__init__.py
app/processors/filters.py
app/processors/formatters.py
app/processors/html_processor.py
app/processors/formatters/__init__.py
app/processors/formatters/code_formatter.py
app/processors/formatters/fern.py
app/processors/formatters/table_formatter.py
app/processors/readers/__init__.py
app/processors/readers/apple_reader.py
app/processors/readers/base.py
app/processors/readers/html_reader.py
app/processors/readers/stack_reader.py
urltomarkdown-1.1.0.dist-info/METADATA
urltomarkdown-1.1.0.dist-info/WHEEL
urltomarkdown-1.1.0.dist-info/entry_points.txt
urltomarkdown-1.1.0.dist-info/top_level.txt
urltomarkdown-1.1.0.dist-info/RECORD
